pyckage/__init__.py
pyckage/__main__.py
pyckage/pyckage.py
pyckage/cli/__init__.py
pyckage/cli/clear.py
pyckage/cli/cli.py
pyckage/cli/config.py
pyckage/cli/deploy.py
pyckage/cli/fix.py
pyckage/cli/pack.py
pyckage/pyckagelib/__init__.py
pyckage/pyckagelib/data.py
pyckage/pyckagelib/error.py
pyckage/pyckagelib/template.py
pyckage/pyckagelib/tracker.py
pyckage/pyckagelib/tree.py
pyckage/pyckagelib/validate.py
pyckage-0.1.1.data/data/pyckage_data/.pyckage-config
pyckage-0.1.1.data/data/pyckage_data/__init__.py.t
pyckage-0.1.1.data/data/pyckage_data/package.t
pyckage-0.1.1.data/data/pyckage_data/setup-data.cfg.t
pyckage-0.1.1.data/data/pyckage_data/setup-github.cfg.t
pyckage-0.1.1.data/data/pyckage_data/setup-plain.cfg.t
pyckage-0.1.1.data/data/pyckage_data/setup-script.cfg.t
pyckage-0.1.1.data/data/pyckage_data/setup.cfg.t
pyckage-0.1.1.data/data/pyckage_data/setup.py.t
pyckage-0.1.1.data/scripts/pyckage
pyckage-0.1.1.dist-info/LICENSE
pyckage-0.1.1.dist-info/METADATA
pyckage-0.1.1.dist-info/WHEEL
pyckage-0.1.1.dist-info/entry_points.txt
pyckage-0.1.1.dist-info/top_level.txt
pyckage-0.1.1.dist-info/RECORD
